{
  "behandlingID": 13,
  "redigerbart": true,
  "saksopplysninger": {},
  "oppsummering": {
    "behandlingstema": {
      "kode": "IKKE_YRKESAKTIV",
      "term": "Ikke yrkesaktiv"
    },
    "behandlingstype": {
      "kode": "SOEKNAD",
      "term": "Søknad"
    },
    "behandlingsstatus": {
      "kode": "UNDER_BEHANDLING",
      "term": "Under behandling"
    },
    "registrertDato": "2018-08-27T07:16:03.273Z",
    "svarFrist": "2020-08-27T07:16:00.000Z",
    "behandlingsfrist": "2018-09-27",
    "sisteOpplysningerHentetDato": "2018-08-10T15:00:00.622Z",
    "endretDato": "2018-08-27T07:16:03.273Z",
    "endretAvNavn": "HATT GLITRENDE",
    "behandlingsresultattype": {
      "kode": "IKKE_FASTSATT",
      "term": "Ikke fastsatt"
    }
  }
}
